[
  {
    "id": "106064361138274326",
    "created_at": "2021-04-14 15:21:53 UTC",
    "url": "https://www.gizmodo.jp/2021/04/sennheiser-mke-400.html",
    "title": "スマホでの動画撮影を高音質に。ゼンハイザーの新マイクはUSB-Cで接続OK"
  },
  {
    "id": "106064405552886852",
    "created_at": "2021-04-14 15:33:11 UTC",
    "url": "https://twitter.com/yonasawa/status/1382297704714280965",
    "title": "マクー on Twitter"
  },
  {
    "id": "106064472061166619",
    "created_at": "2021-04-14 15:50:06 UTC",
    "url": "https://otakinen-museum.note.jp/n/n57366b3c9ad2",
    "title": "「ゴジラ」が描かれた浮世絵の話｜太田記念美術館"
  },
  {
    "id": "106064506501525187",
    "created_at": "2021-04-14 15:58:51 UTC",
    "url": "http://www.macotakara.jp/blog/software/entry-41131.html",
    "title": "コーレル、Apple M1チップに対応したMac仮想化ソリューション「Parallels Desktop 16.5 for Mac」をリリース | ソフトウェア | Macお宝鑑定団 blog（羅針盤）"
  },
  {
    "id": "106064508011963423",
    "created_at": "2021-04-14 15:59:14 UTC",
    "url": "https://watch.amazon.co.jp/detail?gti=amzn1.dv.gti.2ebc2450-051e-6a5c-932d-f1b9d994d2b5&ref_=atv_dp_share_seas&r=web",
    "title": "Amazon.co.jp: TVアニメ「スーパーカブ」を観る | Prime Video"
  },
  {
    "id": "106064547871273730",
    "created_at": "2021-04-14 16:09:23 UTC",
    "url": "https://www.publickey1.jp/blog/21/sf.html",
    "title": "米ガートナー、「スターウォーズの帝国におけるセキュリティは考えうる限り最低スコア」、SF作品に登場する先進文明群をマジッククアドラントで評価。エイプリルフール企画で"
  },
  {
    "id": "106064573435716450",
    "created_at": "2021-04-14 16:15:53 UTC",
    "url": "https://www.publickey1.jp/blog/21/cloudflare_pagesjamwebcdn.html",
    "title": "「Cloudflare Pages」が正式版に。JAMスタックによる高速なWebサイトを構築、CDNに展開へ"
  },
  {
    "id": "106064600768818106",
    "created_at": "2021-04-14 16:22:50 UTC",
    "url": "https://twitter.com/kazuho/status/1382366841591402502?s=20",
    "title": "Kazuho Oku on Twitter"
  },
  {
    "id": "106064622311073582",
    "created_at": "2021-04-14 16:28:18 UTC",
    "url": "https://youtu.be/F8pn7HTqltM",
    "title": "GT-R nismo 2022年モデルの発表会に行ってきた+バルログで頑張るログ"
  },
  {
    "id": "106064626589988708",
    "created_at": "2021-04-14 16:29:24 UTC",
    "url": "https://brave.com/why-brave-disables-floc/",
    "title": "Why Brave Disables FLoC | Brave Browser"
  },
  {
    "id": "106064633419110290",
    "created_at": "2021-04-14 16:31:08 UTC",
    "url": "https://twitter.com/4comapic/status/1381869153372368905?s=21",
    "title": "確定申告が終わったこいしさん on Twitter"
  },
  {
    "id": "106064647074292497",
    "created_at": "2021-04-14 16:34:36 UTC",
    "url": "https://youtu.be/NBQB8yBysng",
    "title": "カメラに載せるだけ！Sonyの新ワイヤレスマイク「ECM-W2BT」がVlogにもYouTube動画にもいい感じ。【先行レビュー】"
  },
  {
    "id": "106064668002840300",
    "created_at": "2021-04-14 16:39:56 UTC",
    "url": "https://twitter.com/kenmaz/status/1381984324157775875?s=12",
    "title": "kenmaz on Twitter"
  },
  {
    "id": "106064685649729661",
    "created_at": "2021-04-14 16:44:25 UTC",
    "url": "https://courrier.jp/news/archives/241271/",
    "title": "徹底してプライバシーを保護する「プライベートブラウザ」がジワジワ来ている | まだChromeとSafariを使ってるの？"
  },
  {
    "id": "106064698068986318",
    "created_at": "2021-04-14 16:47:34 UTC",
    "url": "https://www.teinai.work/entry/marugame201911",
    "title": "丸亀製麺の店舗限定・期間限定メニュードーナツが食べたい！ : ていない（ていねいじゃない暮らしのブログ） Powered by ライブドアブログ"
  },
  {
    "id": "106064790545398106",
    "created_at": "2021-04-14 17:11:05 UTC",
    "url": "https://www.nichigan.or.jp/",
    "title": "\r\n\t日本眼科学会\r\n"
  }
]