[
  {
    "id": "108533161078698515",
    "created_at": "2022-06-24 15:30:11 UTC",
    "url": "https://twitter.com/netatank/status/1540208897436266497",
    "title": "ヨシダ（破産確定） on Twitter"
  },
  {
    "id": "108533185094412081",
    "created_at": "2022-06-24 15:36:17 UTC",
    "url": "https://mainichi.jp/articles/20220624/dde/012/040/003000c",
    "title": "特集ワイド：映画鑑賞、早送りで？　若者に多く　背景に「余裕のなさ」 | 毎日新聞"
  },
  {
    "id": "108533206583472524",
    "created_at": "2022-06-24 15:41:45 UTC",
    "url": "https://youtu.be/4TRGytKf6yU",
    "title": "10年くらい前のカメラに更に古めのレンズをつけてみましたよ。Olympus E-PL1s, Olympus body cap lens 15mm vs Panasonic 14mm - 42mm"
  },
  {
    "id": "108533210714748843",
    "created_at": "2022-06-24 15:42:48 UTC",
    "url": "https://twitter.com/TeimurazLezhava/status/1540167792753664001",
    "title": "駐日ジョージア大使 ティムラズ・レジャバ on Twitter"
  },
  {
    "id": "108533222489514482",
    "created_at": "2022-06-24 15:45:48 UTC",
    "url": "https://twitter.com/little_hand_s/status/1540226666475028480",
    "title": "松岡@ログラス/DDD,アジャイル on Twitter"
  },
  {
    "id": "108533243328892038",
    "created_at": "2022-06-24 15:51:06 UTC",
    "url": "https://mainichi.jp/articles/20220622/k00/00m/050/300000c",
    "title": "森喜朗氏の女性蔑視発言で「議論活発に」　東京五輪を公式に総括 | 毎日新聞"
  },
  {
    "id": "108533259929906614",
    "created_at": "2022-06-24 15:55:19 UTC",
    "url": "https://www.fnn.jp/articles/-/380035",
    "title": "“全市民”情報入ったUSB発見 紛失当日に1人で捜すも...　かばん内の携帯GPSで?"
  },
  {
    "id": "108533260224234383",
    "created_at": "2022-06-24 15:55:24 UTC",
    "url": "https://youtu.be/dsswNklfuV8",
    "title": "drikinさんがスト5をまじめにやりだしたらしいのでそのリプレイを見てあれこれ言ってみる「バルログで頑張るログ」"
  },
  {
    "id": "108533301746284736",
    "created_at": "2022-06-24 16:05:57 UTC",
    "url": "https://twitter.com/hkyamane/status/1540315598521237504",
    "title": "Yasuhiro Yamane/山根康宏 on Twitter"
  },
  {
    "id": "108533359120208590",
    "created_at": "2022-06-24 16:20:33 UTC",
    "url": "https://www.yomiuri.co.jp/politics/20220624-OYT1T50235/",
    "title": "電気代高騰、政府の施策は「ポイント２０００円相当」…各社の節電プログラム参加で"
  },
  {
    "id": "108533413957578857",
    "created_at": "2022-06-24 16:34:29 UTC",
    "url": "https://twitter.com/anime_kaguya/status/1540364148894502912?s=12&t=vKM8sDGkzxfwzzZDTU2y0A",
    "title": "アニメ「かぐや様は告らせたい」公式 on Twitter"
  },
  {
    "id": "108533444789108786",
    "created_at": "2022-06-24 16:42:20 UTC",
    "url": "https://youtu.be/b7KBM470FF4",
    "title": "【6月26日(日)19:59まで】映画『シン・ウルトラマン』本編冒頭10分33秒映像（※48時間限定）"
  }
]