[
  {
    "id": "107847906487327451",
    "created_at": "2022-02-23 15:00:55 UTC",
    "url": "https://www.youtube.com/watch?v=OMdblo4TfwE",
    "title": "【metaQuest】Discord通話がクエスト単体で使えるようになるツール「Oculess」の導入方法、使い方案内します！"
  },
  {
    "id": "107847914720113248",
    "created_at": "2022-02-23 15:03:01 UTC",
    "url": "https://note.com/sifue/n/nc35cf140fc06",
    "title": "Meta Quest単体でMinecraftを動かすQuestCraftの導入方法(1.1.1対応)｜吉村 総一郎 (sifue)｜note"
  },
  {
    "id": "107847944975281660",
    "created_at": "2022-02-23 15:10:43 UTC",
    "url": "https://gigazine.net/news/20220223-trnio-3d-scanner/",
    "title": "スマホ1台で手軽に物体を3Dスキャンできるアプリ「Trnio 3D Scanner」を使ってみた"
  },
  {
    "id": "107847997478867480",
    "created_at": "2022-02-23 15:24:04 UTC",
    "url": "https://note.com/nhk_pr/n/n02b7bbc120fa",
    "title": "「カムカムエヴリバディ」映像表現の裏側｜NHK広報局｜note"
  },
  {
    "id": "107848002593294894",
    "created_at": "2022-02-23 15:25:22 UTC",
    "url": "https://youtu.be/CaxgoP44Phw",
    "title": "シネマティック散歩152【4K HDR】"
  },
  {
    "id": "107848201251134656",
    "created_at": "2022-02-23 16:15:53 UTC",
    "url": "https://steptwo.app/",
    "title": "Step Two"
  },
  {
    "id": "107848242031764554",
    "created_at": "2022-02-23 16:26:15 UTC",
    "url": "https://game.watch.impress.co.jp/docs/news/1389729.html",
    "title": "バレーボール漫画「ハイキュー!!」新作読み切りが掲載決定！ 10周年記念企画の続報公開 10周年記念本、フルカラー版も発売決定"
  }
]