[
  {
    "id": "109846738567284636",
    "created_at": "2023-02-11 15:10:13 UTC",
    "url": "https://twitter.com/hakoiribox/status/1624299898257702913?s=12&t=vTwizarlNsSMT9W9aZLBeQ",
    "title": "ノザキハコネ on Twitter"
  },
  {
    "id": "109846966379269986",
    "created_at": "2023-02-11 16:08:09 UTC",
    "url": "https://news.livedoor.com/article/detail/23689788/",
    "title": "iPhone15シリーズ用USB-CケーブルにMFi認証導入で機能制限？ - ライブドアニュース"
  },
  {
    "id": "109847037331394728",
    "created_at": "2023-02-11 16:26:11 UTC",
    "url": "https://smhn.info/202302-3in1-apple-charger-review",
    "title": "  Appleユーザーなら1つ持っとけ？スマホリング兼用充電器という新機軸 - すまほん!!"
  },
  {
    "id": "109847138604583361",
    "created_at": "2023-02-11 16:51:57 UTC",
    "url": "https://www.nhk.jp/p/ts/EX2P2LNY73/episode/te/YVK2PZQ6M1/",
    "title": "落合陽一、オードリータンについに会う。 - ズームバック×オチアイ"
  },
  {
    "id": "109847165923717210",
    "created_at": "2023-02-11 16:58:53 UTC",
    "url": "https://twitter.com/dmc_cs2a/status/1623997075062153217?s=46&t=0J6qKQWy7rg7_MtHPEdD3A",
    "title": "DAMACHI_DMCS56 on Twitter"
  }
]