[
  {
    "id": "114178402641296826",
    "created_at": "2025-03-17 15:09:21 UTC",
    "url": "https://youtu.be/i61YbEn6zAY?si=yZ8_uwerXGfXJW6P",
    "title": "「ニコンを買わない」は嘘でした。すみません。"
  },
  {
    "id": "114178484110261792",
    "created_at": "2025-03-17 15:30:04 UTC",
    "url": "https://youtu.be/hmo59P4ykT4?si=MjKRYYrgmDW4s1Wy",
    "title": "1332回　トランプ日米同盟に不満！これを機に原潜買っちまえ【左巻き発狂】←『沈黙の艦隊 北極海大海戦』【2025年9月26日(金)公開】"
  },
  {
    "id": "114178516970956425",
    "created_at": "2025-03-17 15:38:25 UTC",
    "url": "https://www.macotakara.jp/sale/entry-48582.html",
    "title": "Amazon、KANICHIのMagSafe対応薄型モバイルバッテリー「KANICHI MS15」を1,980円で販売中（クーポン適用） | 特価 | Mac OTAKARA"
  },
  {
    "id": "114178545666120694",
    "created_at": "2025-03-17 15:45:43 UTC",
    "url": "https://x.com/hermita_akiba/status/1901528730423759017?s=46&t=KYHz1RZsnoI8Ui5FVjeDxA",
    "title": "エルミタージュ秋葉原編集部 (@hermita_akiba) on X"
  },
  {
    "id": "114178548479481519",
    "created_at": "2025-03-17 15:46:26 UTC",
    "url": "https://x.com/nui_colle/status/1901615386078175391?s=46&t=KYHz1RZsnoI8Ui5FVjeDxA",
    "title": "ぬいぬい (@Nui_Colle) on X"
  },
  {
    "id": "114178616612620950",
    "created_at": "2025-03-17 16:03:46 UTC",
    "url": "https://www.macotakara.jp/VisionApp/entry-48583.html",
    "title": "锦泓王、Apple Vision用デスク絵板アプリ「TouchDesk」をリリース | Vision App | Mac OTAKARA"
  },
  {
    "id": "114178621449742570",
    "created_at": "2025-03-17 16:05:00 UTC",
    "url": "https://g-pc.info/archives/40468/",
    "title": "ファーウェイのPC向けマイクロソフト・ウィンドウズ・ライセンスが今月で期限切れ、同社はHarmony OS搭載PCを発売する： レポート - 自作ユーザーが解説するゲーミングPCガイド"
  },
  {
    "id": "114178623427672466",
    "created_at": "2025-03-17 16:05:30 UTC",
    "url": "https://togetter.com/li/2526622",
    "title": "マツケンサンバデザインのアパレル・雑貨がしまむらオンラインストアより販売決定、上様を身に纏えるアイテムが続々"
  }
]