[
  {
    "id": "106862735344344286",
    "created_at": "2021-09-02 15:18:57 UTC",
    "url": "https://youtu.be/bZxYRM80NT4",
    "title": "betcover!!  ワンマンライブ & CD即売会「時間」"
  },
  {
    "id": "106862793180877863",
    "created_at": "2021-09-02 15:33:39 UTC",
    "url": "https://www.nikkan-gendai.com/articles/view/geino/294161",
    "title": "押井守監督「ジブリにボロクソ言えるのは私だけじゃないかと思ったんです」｜日刊ゲンダイDIGITAL"
  },
  {
    "id": "106862926752368476",
    "created_at": "2021-09-02 16:07:37 UTC",
    "url": "https://photosku.com/item/di00180349/",
    "title": "FinePix 1300 - 価格比較：フォトスク"
  }
]