[
  {
    "id": "106930634577318068",
    "created_at": "2021-09-14 15:06:37 UTC",
    "url": "https://youtu.be/lYgwzQWhrcc",
    "title": "Kizawa's VLOG #74 LUMIX G100とZV-1とZV-E10"
  },
  {
    "id": "106930672523227687",
    "created_at": "2021-09-14 15:16:16 UTC",
    "url": "https://youtu.be/j79wuG4J5C8",
    "title": "GoPro: 09.16.21 | A New Era"
  },
  {
    "id": "106930765051082326",
    "created_at": "2021-09-14 15:39:48 UTC",
    "url": "https://www.phileweb.com/news/hobby/202109/14/4838.html",
    "title": "PS5の大型アップデート第2弾、9/15配信。テレビ内蔵SPで3Dオーディオ、M.2 SSDにも対応 - PHILE WEB"
  },
  {
    "id": "106930864256889619",
    "created_at": "2021-09-14 16:05:02 UTC",
    "url": "https://twitter.com/i_m_jimlog/status/1437656121758519296?s=21",
    "title": "牛乳 on Twitter"
  },
  {
    "id": "106930889024591073",
    "created_at": "2021-09-14 16:11:19 UTC",
    "url": "https://www.youtube.com/watch?v=EvGOlAkLSLw",
    "title": "Apple Event — September 14"
  },
  {
    "id": "106930890029690082",
    "created_at": "2021-09-14 16:11:35 UTC",
    "url": "https://youtu.be/m4s8-t3yWsQ",
    "title": "【生配信】ギズモードのAppleイベント実況はこちら！豪華ゲストだ！"
  }
]