[
  {
    "id": "106828689706124681",
    "created_at": "2021-08-27 15:00:42 UTC",
    "url": "https://www.itmedia.co.jp/news/articles/2108/27/news161.html",
    "title": "普通のモニターなのに映像が立体的？　不思議な動画が話題に　「ソニーの“空間再現ディスプレイ”と同じことをもっと安く大画面で」"
  },
  {
    "id": "106828697649840660",
    "created_at": "2021-08-27 15:02:43 UTC",
    "url": "https://www.itmedia.co.jp/news/articles/2108/27/news160.html",
    "title": "アバター着替え放題の大騒ぎ　美少女キャラもロボットも　「バーチャルマーケット6」の遊び方"
  },
  {
    "id": "106828701210796616",
    "created_at": "2021-08-27 15:03:37 UTC",
    "url": "https://www.gizmodo.jp/2021/08/the-new-nest-doorbell-cam-is-a-reminder-that-nest-has-g.html",
    "title": "日本初上陸｢Google Nest Doorbell｣レビュー：安価にドアホンをスマート化できるのはよい。でも賃貸には不向き"
  },
  {
    "id": "106828755515819862",
    "created_at": "2021-08-27 15:17:26 UTC",
    "url": "https://sirabee.com/2021/08/27/20162648008/",
    "title": "ファミマ、8月30日まで「フラッペ」の値段がスゴいことに　これは驚く…"
  },
  {
    "id": "106828769201926344",
    "created_at": "2021-08-27 15:20:55 UTC",
    "url": "https://iphone-mania.jp/news-393055/",
    "title": "折りたたみiPhoneの開発加速〜競合他社の折りたたみスマホ販売好調が刺激"
  },
  {
    "id": "106828870071167309",
    "created_at": "2021-08-27 15:46:34 UTC",
    "url": "https://sirabee.com/2021/08/26/20162647253/",
    "title": "ヒカキンの1000万寄付で新たな説が浮上　じつは「HIKAKIN」ではなかった…？"
  },
  {
    "id": "106828875054958705",
    "created_at": "2021-08-27 15:47:50 UTC",
    "url": "https://youtu.be/v9_PV8aLV2g",
    "title": "DEATH STRANDING DIRECTOR'S CUT - プレビュー トレーラー - [JP] 4K"
  },
  {
    "id": "106828952365508160",
    "created_at": "2021-08-27 16:07:29 UTC",
    "url": "https://twitter.com/FujifilmJP_X/status/1431104318124347399",
    "title": "FUJIFILMXseriesJapan on Twitter"
  },
  {
    "id": "106829043242199035",
    "created_at": "2021-08-27 16:30:36 UTC",
    "url": "https://www.uaudio.jp/uad-plugins/special-processing/c-vox-noise-reduction.html",
    "title": "C-Suite C-Vox Noise & Ambience Reduction | UAD Audio Plugins | Universal Audio"
  }
]