[
  {
    "id": "107394921499621017",
    "created_at": "2021-12-05 15:00:53 UTC",
    "url": "https://www.itmedia.co.jp/news/articles/2112/05/news028.html",
    "title": "「鬼滅の刃 遊郭編」は初回1時間放送、先週までとは別の番組に　録画時の注意点"
  },
  {
    "id": "107394922950975528",
    "created_at": "2021-12-05 15:01:15 UTC",
    "url": "https://youtu.be/4Gg2jFEOMIU",
    "title": "Victory Royal【FortniteVlog#005 】"
  },
  {
    "id": "107394931921393018",
    "created_at": "2021-12-05 15:03:32 UTC",
    "url": "https://www.gizmodo.jp/2021/12/uncensored-library-minecraft-1.html",
    "title": "検閲でバンされた世界中の記事が読める図書館 マインクラフト内で開館"
  },
  {
    "id": "107394941739285448",
    "created_at": "2021-12-05 15:06:02 UTC",
    "url": "https://www.gizmodo.jp/2021/12/sony-airpeak-s1-1st-flight-demonstration-in-japan.html",
    "title": "GMレンズが空を舞う。ソニー珠玉の空撮ドローン｢Airpeak S1｣は、とにかくカッコいいヤツだった"
  },
  {
    "id": "107395019469883324",
    "created_at": "2021-12-05 15:25:48 UTC",
    "url": "https://taisy0.com/2021/12/03/149329.html",
    "title": "Appleのティム・クックCEOが2026年に辞任するという噂"
  },
  {
    "id": "107395128516197594",
    "created_at": "2021-12-05 15:53:32 UTC",
    "url": "https://youtu.be/WUgXOvWJyF0",
    "title": "テキサス旅行3日目"
  },
  {
    "id": "107395148019979370",
    "created_at": "2021-12-05 15:58:30 UTC",
    "url": "https://mamerica.net/4163",
    "title": "身近に潜むテキサスの危険動物トップ6、都市部に住んでいても油断は禁物！ | mAmerica"
  },
  {
    "id": "107395151054895361",
    "created_at": "2021-12-05 15:59:16 UTC",
    "url": "https://www.youtube.com/watch?v=IIjRaNzRmL0",
    "title": "世界最大級のVRイベント！バーチャルマーケット2021が凄すぎる！"
  },
  {
    "id": "107395204842739746",
    "created_at": "2021-12-05 16:12:57 UTC",
    "url": "https://youtu.be/dTEIxAJKR88",
    "title": "テキサス旅行4日目"
  },
  {
    "id": "107395214826927838",
    "created_at": "2021-12-05 16:15:29 UTC",
    "url": "https://youtu.be/v0RsP41MFaQ",
    "title": "ヨドコウ桜スタジアムで川崎サポしてきた"
  },
  {
    "id": "107395223658302776",
    "created_at": "2021-12-05 16:17:44 UTC",
    "url": "https://youtu.be/jFBF9J9SCDU",
    "title": "リアルアバターを青山3Dスキャンスタジオで作ってVRChatにアップしてみた"
  },
  {
    "id": "107396497258190989",
    "created_at": "2021-12-05 21:41:37 UTC",
    "url": "https://gendai.ismedia.jp/articles/-/89928?utm_source=smartnews&utm_medium=ios&utm_campaign=app",
    "title": "日本人の「魚離れ」を加速させた、大手スーパーの魚売り場の「重い責任」（川本 大吾） @moneygendai"
  },
  {
    "id": "107396961235659090",
    "created_at": "2021-12-05 23:39:37 UTC",
    "url": "https://youtu.be/jjDIZ3gWWaY",
    "title": "富士五湖紅葉と時之栖イルミネーション"
  },
  {
    "id": "107397042343031214",
    "created_at": "2021-12-06 00:00:15 UTC",
    "url": "https://t.co/r2xQbFbhbb",
    "title": "蝉ばいと@そうめん派 on Twitter"
  },
  {
    "id": "107397113599635017",
    "created_at": "2021-12-06 00:18:22 UTC",
    "url": "https://www.skylark.co.jp/jonathan/menu/menu_detail.html?mid=361_24409",
    "title": "おかずプレート | 大皿／盛り合わせ | ジョナサン | すかいらーくグループ"
  },
  {
    "id": "107397294362706421",
    "created_at": "2021-12-06 01:04:20 UTC",
    "url": "https://cweb.canon.jp/satera/mfp/lineup/a4-mono/mf232w/",
    "title": "キヤノン：スモールオフィス向け複合機 Satera MF232w｜概要"
  },
  {
    "id": "107397343117292606",
    "created_at": "2021-12-06 01:16:44 UTC",
    "url": "https://news.yahoo.co.jp/articles/9c32f06e2c490de53b598465dc28be7172727751",
    "title": "J2大宮　残留も続くいばら道、大口スポンサー・ドコモ来季撤退も（スポニチアネックス） - Yahoo!ニュース"
  },
  {
    "id": "107397462003821252",
    "created_at": "2021-12-06 01:46:58 UTC",
    "url": "https://www.jha.or.jp/jp/shop/products/yachting/index.html",
    "title": "ヨット・モータボート用参考図(Yチャート) | 海図ネットショップ | 日本水路協会"
  },
  {
    "id": "107397540647945534",
    "created_at": "2021-12-06 02:06:58 UTC",
    "url": "https://youtu.be/329Z2_V8hKk",
    "title": "シネマティック散歩73"
  },
  {
    "id": "107397660618666170",
    "created_at": "2021-12-06 02:37:29 UTC",
    "url": "https://hochi.news/articles/20211205-OHT1T51227.html",
    "title": "新チェアマン内定の野々村芳和氏…コロナ楽観視せずリーグに進言、ノストラダムスならぬ「野々村ダムス」"
  },
  {
    "id": "107397671358010401",
    "created_at": "2021-12-06 02:40:13 UTC",
    "url": "http://www.macotakara.jp/blog/accessories/entry-42130.html",
    "title": "Apple Store、BelkinのApple Watch磁気高速充電対応充電器「Belkin BOOST↑CHARGE PRO Portable Fast Charger for Apple Watch」を販売開始 | アクセサリ | Macお宝鑑定団 blog（羅針盤）"
  },
  {
    "id": "107397680256365887",
    "created_at": "2021-12-06 02:42:28 UTC",
    "url": "http://www.macotakara.jp/blog/accessories/entry-42131.html",
    "title": "Apple Store、BelkinのApple Watch磁気高速充電とMagSafe&Qiワイヤレス充電に対応した充電台「Belkin BOOST↑CHARGE PRO 3-in-1 Wireless Charging Pad with MagSafe」を販売開始 | アクセサリ | Macお宝鑑定団 blog（羅針盤）"
  },
  {
    "id": "107397793041815772",
    "created_at": "2021-12-06 03:11:09 UTC",
    "url": "https://www.youtube.com/watch?v=OZrlUMFsHLc",
    "title": "テキサス旅行５日目"
  },
  {
    "id": "107397822690862477",
    "created_at": "2021-12-06 03:18:42 UTC",
    "url": "https://www.watch.impress.co.jp/docs/news/1371786.html",
    "title": "月5000円で乗り放題の共有交通「mobi」。名古屋で開始"
  },
  {
    "id": "107397882338885883",
    "created_at": "2021-12-06 03:33:52 UTC",
    "url": "https://youtu.be/Q7y7cdJEpV0",
    "title": "「テキサス旅行5日目、背筋崩壊！ビッグ・ベンドのカヤックはガチだがやっぱり大自然は素晴らしい！」第1507話"
  },
  {
    "id": "107397895847329448",
    "created_at": "2021-12-06 03:37:18 UTC",
    "url": "https://youtube.com/watch?v=AV7_NILt2kI&feature=share",
    "title": "VLOG 163　J1リーグ最終戦パナソニックスタジアム吹田へGo!!"
  },
  {
    "id": "107397927220615482",
    "created_at": "2021-12-06 03:45:17 UTC",
    "url": "https://twitter.com/ray_strb/status/1467376302940655616?s=12",
    "title": "フジイレイ(ゆるダイエット中) on Twitter"
  },
  {
    "id": "107397952892089050",
    "created_at": "2021-12-06 03:51:48 UTC",
    "url": "https://youtu.be/XmIDISbU1JQ",
    "title": "自動運転ドローンSkydioとジョンラセターのワイナリー #532 [4K] [GH5] drone 旅行"
  },
  {
    "id": "107397957760862918",
    "created_at": "2021-12-06 03:53:03 UTC",
    "url": "https://youtu.be/1k2uQ_Il_N8",
    "title": "【悲報】自動運転ドローン墜落 ミューア・ウッズの悲劇 #582 #4K #a7III"
  },
  {
    "id": "107398082710779639",
    "created_at": "2021-12-06 04:24:49 UTC",
    "url": "https://flowers.naked.works/kochi-castle/",
    "title": "NAKED FLOWERS -高知城- 百花繚乱ぜよ! | NAKED, INC."
  },
  {
    "id": "107398292816263712",
    "created_at": "2021-12-06 05:18:15 UTC",
    "url": "https://av.watch.impress.co.jp/docs/series/zooma/1370328.html",
    "title": "古い機器もLDAC対応で蘇る! BluetoothメディアHUB、FiiO「BTA30 Pro」【小寺信良の週刊 Electric Zooma!】"
  },
  {
    "id": "107398295344764508",
    "created_at": "2021-12-06 05:18:54 UTC",
    "url": "https://www.youtube.com/watch?v=4nSDv2ta-SE",
    "title": "もぐラジオ第67回（2021年12月06日）〜韓国がメタバースに積極的な理由、VTuberキズナアイ無期限休止など〜"
  },
  {
    "id": "107398593053887947",
    "created_at": "2021-12-06 06:34:37 UTC",
    "url": "https://www.quicpay.jp/about/quicpayplus.html",
    "title": "QUICPayとQUICPay＋の違い"
  },
  {
    "id": "107398611001297822",
    "created_at": "2021-12-06 06:39:10 UTC",
    "url": "https://www.youtube.com/watch?v=lefIV6g937g",
    "title": "【Oculus Quest 2】VRゲームデータをクラウド上に保存出来る！？本格的なMR撮影も可能に！V35アップデート内容が凄い！"
  },
  {
    "id": "107398722383277994",
    "created_at": "2021-12-06 07:07:30 UTC",
    "url": "https://response.jp/article/2021/12/05/351982.html",
    "title": "「こいつ…、動くぞ」総排気量7ccの超小型エンジン組み立てキット　予約開始 | レスポンス（Response.jp）"
  },
  {
    "id": "107398782613270783",
    "created_at": "2021-12-06 07:22:49 UTC",
    "url": "https://japanese.engadget.com/apple-airtag-car-thefts-canada-025912194.html",
    "title": "AirTagが車泥棒に悪用される事件増加、高級車に付けて自宅まで追跡 - Engadget 日本版"
  },
  {
    "id": "107398895292127612",
    "created_at": "2021-12-06 07:51:28 UTC",
    "url": "https://youtu.be/41AaC_CRv5w",
    "title": "NYキャスターが見た年末商戦【基礎から解説アメリカ経済#2】（2021年12月6日）"
  },
  {
    "id": "107398917687752804",
    "created_at": "2021-12-06 07:57:10 UTC",
    "url": "https://www.gizmodo.jp/2021/12/hidden-features-in-macos-monterey-worth-finding.html",
    "title": "macOS Montereyの隠れた便利機能12選"
  },
  {
    "id": "107398953869375146",
    "created_at": "2021-12-06 08:06:22 UTC",
    "url": "https://support.oculus.com/articles/in-vr-experiences/oculus-features/mobile-mixed-reality-camera",
    "title": "Casting with Mobile Mixed Reality Camera on Quest"
  },
  {
    "id": "107399000108333718",
    "created_at": "2021-12-06 08:18:08 UTC",
    "url": "https://note.com/backspacefm/n/n6d931e35cbf9",
    "title": "BSMポッドキャスト始めました！登録方法を解説します｜Backspace Magazine｜note"
  },
  {
    "id": "107399132024604432",
    "created_at": "2021-12-06 08:51:41 UTC",
    "url": "https://open.spotify.com/wrapped-2021/share-3f0cd96215434f2d87f08e7b9bcc9485-1080x1920?si=AUiLGUZcQBqO05QjkxS2dQ&lang=ja",
    "title": "Your 2021 Wrapped"
  },
  {
    "id": "107399153654030189",
    "created_at": "2021-12-06 08:57:11 UTC",
    "url": "https://open.spotify.com/wrapped-2021/share-ff6d753cf7ba47f7b999c0b141435e9e-1080x1920?si=_vB_4nEkQvSNoCmhopIOYQ&lang=ja",
    "title": "Your 2021 Wrapped"
  },
  {
    "id": "107399319360677736",
    "created_at": "2021-12-06 09:39:19 UTC",
    "url": "https://gigazine.net/news/20211206-airtag-car/",
    "title": "Apple製落とし物トラッカー「AirTag」が車泥棒に利用されている実態を警察が報告、対策方法は？"
  },
  {
    "id": "107399358362978819",
    "created_at": "2021-12-06 09:49:14 UTC",
    "url": "https://www.huffingtonpost.jp/entry/covid19-fake-arm_jp_61ad6cbce4b0ae9a42be5570",
    "title": "「何かがおかしい」偽物の腕でワクチン接種しようとした男性。看護師が見破る"
  },
  {
    "id": "107399423202666567",
    "created_at": "2021-12-06 10:05:44 UTC",
    "url": "https://www.fnn.jp/articles/-/280960",
    "title": "アウトドアに高耐久ケータイ　防水・耐衝撃 クマ用ブザーも"
  },
  {
    "id": "107399441180535738",
    "created_at": "2021-12-06 10:10:18 UTC",
    "url": "https://www.moguravr.com/zepeto-3/",
    "title": "スマホアプリ「ZEPETO」の遊び方を紹介 3Dアバターでオシャレを楽しもう！ | Mogura VR"
  },
  {
    "id": "107399503107356526",
    "created_at": "2021-12-06 10:26:03 UTC",
    "url": "https://twitter.com/livedoornews/status/1467773133205958658",
    "title": "ライブドアニュース on Twitter"
  },
  {
    "id": "107399517384972363",
    "created_at": "2021-12-06 10:29:41 UTC",
    "url": "https://youtu.be/Sv8BzW01x-Y",
    "title": "FPV Drone Vs Rallycross Cars"
  },
  {
    "id": "107399558578830579",
    "created_at": "2021-12-06 10:40:09 UTC",
    "url": "https://www.gizmodo.jp/2021/12/nvidia-gaugan2.html",
    "title": "絵心ゼロでもOK！NVIDIAのAIが3～4単語の文章から写実的な画像を生成できるようになる"
  },
  {
    "id": "107399570968148041",
    "created_at": "2021-12-06 10:43:18 UTC",
    "url": "http://gadgetlove.blog18.fc2.com/blog-entry-987.html",
    "title": "「モノが好き」2 - ＜感動＞ ピヤホン5！"
  },
  {
    "id": "107399589494487471",
    "created_at": "2021-12-06 10:48:01 UTC",
    "url": "https://www.itmedia.co.jp/news/articles/2112/06/news061.html",
    "title": "ふとんでのスマホいじりはもっての外！　SNSの「イイネ」が「いい眠り」を阻害"
  },
  {
    "id": "107399606279881431",
    "created_at": "2021-12-06 10:52:17 UTC",
    "url": "http://touchlab.jp/2021/12/kindle_winter_sale_2021dec/",
    "title": "【対象4万冊】50%ポイント還元「Kindle本冬のキャンペーン」が開催中"
  },
  {
    "id": "107399620162010186",
    "created_at": "2021-12-06 10:55:49 UTC",
    "url": "https://japanese.engadget.com/kddi-010049240.html",
    "title": "9年ぶりG'zOne復活。KDDIが高耐久ケータイ「G'zOne TYPE-XX」を10日発売　その背景に迫る（石野純也） - Engadget 日本版"
  },
  {
    "id": "107399656395889252",
    "created_at": "2021-12-06 11:05:02 UTC",
    "url": "https://www.gizmodo.jp/2021/12/huawei-ultrathin-keyboard.html",
    "title": "ファーウェイの超薄型で多機能な無線キーボード。USB-C充電で12カ月使える"
  },
  {
    "id": "107399663131269932",
    "created_at": "2021-12-06 11:06:45 UTC",
    "url": "https://japanese.engadget.com/urbanista-los-angels-review-031507557.html",
    "title": "太陽光発電ヘッドホン「urbanista LOS ANGELES」レビュー。晴天なら無限再生も可能 - Engadget 日本版"
  },
  {
    "id": "107399692870213974",
    "created_at": "2021-12-06 11:14:18 UTC",
    "url": "https://www.gizmodo.jp/2021/12/wall-kashitsuki.html",
    "title": "人感センサーでアルコール消毒用としても。ハイブリッドな壁掛けライト兼用加湿器"
  },
  {
    "id": "107399696040972340",
    "created_at": "2021-12-06 11:15:07 UTC",
    "url": "https://japanknowledge.com/articles/blognihongo/entry.html?entryid=489",
    "title": "「キューピー」と「キユーピー」 : 日本語、どうでしょう？"
  },
  {
    "id": "107399700003456265",
    "created_at": "2021-12-06 11:16:07 UTC",
    "url": "https://www.itmedia.co.jp/news/articles/2112/06/news111.html",
    "title": "前澤友作氏のISSへの打ち上げは12月8日　NASAがライブ配信"
  },
  {
    "id": "107399724154294242",
    "created_at": "2021-12-06 11:22:16 UTC",
    "url": "https://www.gizmodo.jp/2021/12/processing-speed-of-snapdragon-will-be-greatly-increased.html",
    "title": "スナドラとWindows 11のタッグ、来年にはM1のMacBookに性能比で迫る？"
  },
  {
    "id": "107399756560152852",
    "created_at": "2021-12-06 11:30:30 UTC",
    "url": "https://motor-fan.jp/weboption/article/20681/",
    "title": "「日本初の6ローターエンジン製作進行中！」お披露目は東京オートサロン2022か!?"
  },
  {
    "id": "107399763361334223",
    "created_at": "2021-12-06 11:32:14 UTC",
    "url": "https://ledge.ai/datagrid-japanese-idol-re-posting/",
    "title": "「なにこれすごい」「適度な普通感！」AIが生成した架空のアイドル | Ledge.ai"
  },
  {
    "id": "107399813649622823",
    "created_at": "2021-12-06 11:45:01 UTC",
    "url": "https://www.watch.impress.co.jp/docs/news/1371843.html",
    "title": "文章を読むスピードが最大2倍。「読書アシスト」無償公開"
  },
  {
    "id": "107399821062537778",
    "created_at": "2021-12-06 11:46:55 UTC",
    "url": "https://internet.watch.impress.co.jp/docs/yajiuma/1371759.html",
    "title": "予想より長い歴史が！？ 世界初の電子書籍の公開から今月で「50周年」を迎える【やじうまWatch】"
  },
  {
    "id": "107399911571261530",
    "created_at": "2021-12-06 12:09:56 UTC",
    "url": "https://www.webuomo.jp/life/184140/",
    "title": "【おしゃれな大人の家電】南貴之も絶賛。パナソニックのレイアウトフリーテレビを買うべきつ5の理由"
  },
  {
    "id": "107399958814133021",
    "created_at": "2021-12-06 12:21:56 UTC",
    "url": "https://hobby.watch.impress.co.jp/docs/news/1370798.html",
    "title": "パナソニックの「LUMIX Gシリーズ DC-GH5M2」が約11.2万円！ 「楽天スーパーSALE」にて5台限定 12月10日21時30分より販売"
  },
  {
    "id": "107399966506031992",
    "created_at": "2021-12-06 12:23:54 UTC",
    "url": "https://news.kddi.com/kddi/corporate/newsrelease/2021/12/06/5579.html",
    "title": "au、耐久性に優れたG'zOne20周年記念モデル「G'zOne TYPE-XX」を12月10日から発売"
  },
  {
    "id": "107399970038191734",
    "created_at": "2021-12-06 12:24:48 UTC",
    "url": "https://japan.cnet.com/article/35180453/",
    "title": "LINE Pay、一部ユーザーのキャンペーン参加情報が漏えい--GitHub上で閲覧できる状態に"
  },
  {
    "id": "107399972159590811",
    "created_at": "2021-12-06 12:25:20 UTC",
    "url": "https://togetter.com/li/1812342",
    "title": "「味付けはお前が決めんだよ」料理研究家リュウジおにいさんが「少々」「ひとつまみ」などわかりにくい用語をズバッと解説"
  },
  {
    "id": "107399983523292045",
    "created_at": "2021-12-06 12:28:13 UTC",
    "url": "https://www.itmedia.co.jp/news/articles/2112/06/news157.html",
    "title": "訓練なしにWebサイトを最大2倍速く読めるように　Chrome用拡張機能を無償公開　日本ユニシス"
  },
  {
    "id": "107399988339347647",
    "created_at": "2021-12-06 12:29:27 UTC",
    "url": "https://news.yahoo.co.jp/articles/8a9e49572b47ab964b3b15b07fc2790dcdac711f",
    "title": "楽天、送料無料は独禁法違反疑い　出店者に不利益、公取委が指摘（共同通信） - Yahoo!ニュース"
  },
  {
    "id": "107399997388987099",
    "created_at": "2021-12-06 12:31:45 UTC",
    "url": "https://fujifilm-x.com/ja-jp/stories/medium-format-cinema-camera-supported-by-blackmagic-raw/",
    "title": "Blackmagic RAW収録対応でGFX100Sが「中判シネマカメラ」へと変化する |  | 富士フイルム Xシリーズ & GFX"
  },
  {
    "id": "107400032332421638",
    "created_at": "2021-12-06 12:40:38 UTC",
    "url": "http://www.macotakara.jp/blog/news/entry-42132.html",
    "title": "12月20日から、マイナンバーカードを使い、スマートフォンによって、国内外で利用できるワクチン接種証明書を入手可能に | NEWS | Macお宝鑑定団 blog（羅針盤）"
  },
  {
    "id": "107400046405906653",
    "created_at": "2021-12-06 12:44:13 UTC",
    "url": "https://youtu.be/lWEmCcuvUnM",
    "title": "教育系YouTuberにならない方がいい7つの理由"
  },
  {
    "id": "107400111341336667",
    "created_at": "2021-12-06 13:00:44 UTC",
    "url": "https://youtu.be/l0lMowr2Qr4",
    "title": "【焚火会】ヒロシとTikTokerとキャンプ芸人とステーキ鉄板焼き"
  },
  {
    "id": "107400244569397776",
    "created_at": "2021-12-06 13:34:37 UTC",
    "url": "https://www.tokeibegin.jp/feature/29422/",
    "title": "チューダーがシルバー925を採用した理由は？ | 特集 | 時計Begin.jp"
  },
  {
    "id": "107400250873794465",
    "created_at": "2021-12-06 13:36:13 UTC",
    "url": "https://twitter.com/taka64_/status/1467826594492588032?s=12",
    "title": "遊 on Twitter"
  },
  {
    "id": "107400413225226833",
    "created_at": "2021-12-06 14:17:30 UTC",
    "url": "https://nico.ms/sm39101100",
    "title": "アニソン2on2ダンスバトル『あきばっか～のvol.23』ベスト8第四試合"
  },
  {
    "id": "107400430879809889",
    "created_at": "2021-12-06 14:22:00 UTC",
    "url": "https://twitter.com/frc_watashi_ame/status/1467684975005028352?s=21",
    "title": "ゆとぴ@アメコミ映画＆フィギュア情報/トイハコ/FRC on Twitter"
  },
  {
    "id": "107400433211716367",
    "created_at": "2021-12-06 14:22:35 UTC",
    "url": "https://moov.ooo/article/61ab49f6cca2e864484fe638",
    "title": "スライドさせて秒で装着！ LDACに対応したハイレゾ並の完全ワイヤレスイヤホン「X-BOAT PRO」 - bouncy / バウンシー"
  },
  {
    "id": "107400453727047354",
    "created_at": "2021-12-06 14:27:48 UTC",
    "url": "https://youtu.be/UVmXRxcqNHE",
    "title": "木下百花 \"えっちなこと\"(Official Music Video)"
  },
  {
    "id": "107400545482078674",
    "created_at": "2021-12-06 14:51:08 UTC",
    "url": "https://monoist.itmedia.co.jp/mn/articles/2112/06/news012.html",
    "title": "3Dプリンタで製作するオフィス家具デザインのプロジェクトを発表"
  },
  {
    "id": "107400570337903808",
    "created_at": "2021-12-06 14:57:28 UTC",
    "url": "https://twitter.com/1738310/status/1467715229010526208?s=21",
    "title": "共立出版 アリがと蟻 on Twitter"
  }
]