[
  {
    "id": "110667764687421141",
    "created_at": "2023-07-06 15:07:57 UTC",
    "url": "https://www.itmedia.co.jp/news/articles/2307/06/news160.html",
    "title": "Threadsの投稿をTwitterに共有する方法　2タップでサクッと"
  },
  {
    "id": "110667768627063814",
    "created_at": "2023-07-06 15:08:57 UTC",
    "url": "https://www.threads.net/t/CuWUdXmyvlj/?igshid=NTc4MTIwNjQ2YQ==",
    "title": "ARuFa (@arufa_faru) on Threads"
  },
  {
    "id": "110667777053467822",
    "created_at": "2023-07-06 15:11:06 UTC",
    "url": "https://www.itmedia.co.jp/news/articles/2307/06/news189.html",
    "title": "ペダルを回さない「電動サイクル」、glafitが一般販売へ　「特定原付＝電動キックボードは誤解」"
  },
  {
    "id": "110667790879103704",
    "created_at": "2023-07-06 15:14:37 UTC",
    "url": "https://www.gizmodo.jp/2023/07/denonperlpro.html",
    "title": "イヤホン探し完結？｢Denon PerL Pro｣が提示した新たな回答"
  },
  {
    "id": "110667798791182159",
    "created_at": "2023-07-06 15:16:37 UTC",
    "url": "https://www.threads.net/t/CuWO7X0ru-a/?igshid=NTc4MTIwNjQ2YQ==",
    "title": "森 シェフ (@pasta.mori) on Threads"
  },
  {
    "id": "110667962822055198",
    "created_at": "2023-07-06 15:58:20 UTC",
    "url": "https://mastodon.social/@Mastodon/110667890329356603",
    "title": "Mastodon (@Mastodon@mastodon.social)"
  },
  {
    "id": "110668178854904472",
    "created_at": "2023-07-06 16:53:17 UTC",
    "url": "https://www.phileweb.com/news/d-av/202307/06/58479.html",
    "title": "JBL、自転車のハンドルに取付可能なポータブルスピーカー「JBL WIND 3」 - PHILE WEB"
  }
]