[
  {
    "id": "110735861472188356",
    "created_at": "2023-07-18 15:45:51 UTC",
    "url": "https://www.youtube.com/live/UrdEUMyHdR8?feature=share",
    "title": "『君たちはどう生きるか』を、私たちはどう観たのか【完全ネタバレ感想大会】　高橋ヨシキ+柳下毅一郎+てらさわホーク #blackholetv"
  },
  {
    "id": "110735966705834075",
    "created_at": "2023-07-18 16:12:37 UTC",
    "url": "https://www.publickey1.jp/blog/23/bing_chat_enterprise5inspire_2023.html",
    "title": "［速報］マイクロソフト、企業向け「Bing Chat Enterprise」プレビュー開始、個人ユーザーも月額5ドルで利用可能。Inspire 2023"
  }
]